nada_ai/__init__.py
nada_ai/client/__init__.py
nada_ai/client/clients/__init__.py
nada_ai/client/clients/prophet.py
nada_ai/client/clients/sklearn.py
nada_ai/client/clients/torch.py
nada_ai/client/model_client.py
nada_ai/exceptions.py
nada_ai/linear_model/__init__.py
nada_ai/linear_model/linear_regression.py
nada_ai/linear_model/logistic_regression.py
nada_ai/nada_typing.py
nada_ai/nn/__init__.py
nada_ai/nn/module.py
nada_ai/nn/modules/__init__.py
nada_ai/nn/modules/conv.py
nada_ai/nn/modules/distance.py
nada_ai/nn/modules/flatten.py
nada_ai/nn/modules/linear.py
nada_ai/nn/modules/pooling.py
nada_ai/nn/modules/relu.py
nada_ai/nn/parameter.py
nada_ai/time_series/__init__.py
nada_ai/time_series/prophet.py
nada_ai/utils.py
nada_ai-0.6.0.dist-info/LICENSE
nada_ai-0.6.0.dist-info/METADATA
nada_ai-0.6.0.dist-info/WHEEL
nada_ai-0.6.0.dist-info/RECORD
