Metadata-Version: 2.1
Name: nada-ai
Version: 0.6.0
Summary: Nada-AI is a Python library designed for AI/ML on top of Nada DSL and Nillion Network.
Author: Mathias Leys
Author-email: mathias.leys@nillion.com
Requires-Python: >=3.10,<4.0
Classifier: Programming Language :: Python :: 3
Classifier: Programming Language :: Python :: 3.10
Classifier: Programming Language :: Python :: 3.11
Classifier: Programming Language :: Python :: 3.12
Classifier: Programming Language :: Python :: 3.13
Provides-Extra: examples
Provides-Extra: linter
Requires-Dist: black (>=24.4.2,<25.0.0) ; extra == "linter"
Requires-Dist: isort (>=5.13.2,<6.0.0) ; extra == "linter"
Requires-Dist: nada-numpy (>=0.6.0,<0.7.0)
Requires-Dist: nillion-python-helpers (>=0.3.1,<0.4.0)
Requires-Dist: prophet (>=1.1.5,<2.0.0)
Requires-Dist: scikit-learn (>=1.4.2,<2.0.0)
Requires-Dist: torch (>=2.0.0,<3.0.0)
Requires-Dist: torchvision (>=0.18.1,<0.19.0) ; extra == "examples"
